rosbackup/__init__.py
rosbackup/__main__.py
rosbackup/main.py
rosbackup/rosdevice.py
rosbackup-1.1.0.dist-info/LICENSE
rosbackup-1.1.0.dist-info/METADATA
rosbackup-1.1.0.dist-info/WHEEL
rosbackup-1.1.0.dist-info/entry_points.txt
rosbackup-1.1.0.dist-info/top_level.txt
rosbackup-1.1.0.dist-info/RECORD
