Metadata-Version: 2.1
Name: rosbackup
Version: 1.1.0
Summary: RouterOS config backup tool
Home-page: https://github.com/mharjac/rosbackup
Author: Mario Harjac
Author-email: m@harja.ch
License: UNKNOWN
Platform: UNKNOWN
Classifier: Programming Language :: Python :: 3
Classifier: License :: OSI Approved :: MIT License
Classifier: Operating System :: OS Independent
Requires-Python: >=3.6
Requires-Dist: netmiko
